modulitiz_mini/ModuloRsa.py
modulitiz_mini/django/ModuloDjango.py
modulitiz_mini/django/MyMiddleware.py
modulitiz_mini/django/settings.py
modulitiz_mini/files/pdf/AbstractPdf.py
modulitiz_mini/files/pdf/ReadPdf.py
modulitiz_mini/files/pdf/WritePdf.py
modulitiz_mini/multimedia/ModuloMultimedia.py
modulitiz_mini/rete/ModuloTor.py
modulitiz_mini/rete/ftp/FtpReturnBean.py
modulitiz_mini/rete/ftp/ModuloFtp.py
modulitiz_mini-2.10.0.dist-info/licenses/LICENSE
modulitiz_mini-2.10.0.dist-info/METADATA
modulitiz_mini-2.10.0.dist-info/WHEEL
modulitiz_mini-2.10.0.dist-info/top_level.txt
modulitiz_mini-2.10.0.dist-info/RECORD
