Metadata-Version: 2.4
Name: modulitiz_mini
Version: 2.10.0
Summary: Raccolta dei miei moduli - versione mini
Author-email: tiz <sderfo1234@altervista.org>
Classifier: Programming Language :: Python :: 3
Classifier: Operating System :: OS Independent
Requires-Python: >=3.11
License-File: LICENSE
Requires-Dist: modulitiz-binaries>=2
Requires-Dist: cryptography>=41.0
Requires-Dist: pypdf==6.6.0
Dynamic: license-file
